wagtail_webstories/__init__.py
wagtail_webstories/admin_urls.py
wagtail_webstories/apps.py
wagtail_webstories/blocks.py
wagtail_webstories/forms.py
wagtail_webstories/markup.py
wagtail_webstories/models.py
wagtail_webstories/views.py
wagtail_webstories/wagtail_hooks.py
wagtail_webstories/migrations/0001_initial.py
wagtail_webstories/migrations/0002_extend_url_hash.py
wagtail_webstories/migrations/__init__.py
wagtail_webstories/templates/wagtail_webstories/base_web_story_page.html
wagtail_webstories/templates/wagtail_webstories/admin/import.html
wagtail_webstories/templates/wagtail_webstories/blocks/external_story_embed_block.html
wagtail_webstories/templates/wagtail_webstories/blocks/external_story_poster_link.html
wagtail_webstories/templates/wagtail_webstories/blocks/story_embed_block.html
wagtail_webstories/templates/wagtail_webstories/blocks/story_poster_link.html
wagtail_webstories-0.1.1.dist-info/LICENSE
wagtail_webstories-0.1.1.dist-info/METADATA
wagtail_webstories-0.1.1.dist-info/WHEEL
wagtail_webstories-0.1.1.dist-info/top_level.txt
wagtail_webstories-0.1.1.dist-info/RECORD
