Metadata-Version: 2.1
Name: wagtail-webstories
Version: 0.1.1
Summary: AMP web story support for Wagtail
Home-page: https://github.com/torchbox/wagtail-webstories/
Author: Matt Westcott
Author-email: matthew@torchbox.com
License: BSD
Classifier: Development Status :: 4 - Beta
Classifier: Environment :: Web Environment
Classifier: Intended Audience :: Developers
Classifier: Programming Language :: Python :: 3
Classifier: Framework :: Django
Classifier: Framework :: Django :: 3
Classifier: Framework :: Django :: 4
Classifier: Framework :: Wagtail
Classifier: Framework :: Wagtail :: 4
Classifier: Framework :: Wagtail :: 5
Classifier: Topic :: Internet :: WWW/HTTP
Classifier: License :: OSI Approved :: BSD License
Classifier: Operating System :: OS Independent
Requires-Python: >=3.8
License-File: LICENSE
Requires-Dist: wagtail (>=4.1)
Requires-Dist: webstories (<1,>=0.0.1)
Requires-Dist: requests (<3,>=2.24.0)
Requires-Dist: beautifulsoup4 (<5,>=4.6)
Provides-Extra: testing
Requires-Dist: responses (<1,>=0.12) ; extra == 'testing'
Requires-Dist: Pillow (<10.0.0,>=4.0.0) ; extra == 'testing'
Requires-Dist: wagtailmedia (<0.15,>=0.6) ; extra == 'testing'
